hacker.py
hacker_tools.py
index.py
reimagined_spoon-0.4.1.dist-info/METADATA
reimagined_spoon-0.4.1.dist-info/WHEEL
reimagined_spoon-0.4.1.dist-info/top_level.txt
reimagined_spoon-0.4.1.dist-info/RECORD
