Metadata-Version: 2.1
Name: reimagined-spoon
Version: 0.4.1
Summary: Spoon for testing
Home-page: https://github.com/Jalkhov/reimagined-spoon
Author: Pedro Torcatt
Author-email: pedrotorcattsoto@gmail.com
License: UNKNOWN
Project-URL: Bug Reports, https://github.com/Jalkhov/reimagined-spoon/issues
Project-URL: Source, https://github.com/Jalkhov/reimagined-spoon
Platform: UNKNOWN
Requires-Python: >=3.6
